{
  "sections": {
    "16468903570d47cd4d": {
      "type": "image-banner",
      "blocks": {
        "16468903571974ebaa-0": {
          "type": "heading",
          "settings": {
            "heading": "Let's Chat",
            "heading_size": "medium"
          }
        }
      },
      "block_order": ["16468903571974ebaa-0"],
      "settings": {
        "image": "shopify://shop_images/jason-wang-NxAwryAbtIw-unsplash_1.jpg",
        "image_overlay_opacity": 0,
        "image_height": "small",
        "adapt_height_first_image": false,
        "desktop_content_position": "middle-center",
        "show_text_box": false,
        "desktop_content_alignment": "center",
        "color_scheme": "background-1",
        "mobile_content_alignment": "center",
        "stack_images_on_mobile": true,
        "show_text_below": false
      }
    },
    "16512324026110f03c": {
      "type": "rich-text",
      "blocks": {
        "1651232402df3cc1c0-0": {
          "type": "heading",
          "settings": {
            "heading": "Contact Us!",
            "heading_size": "h1"
          }
        },
        "1651232402df3cc1c0-1": {
          "type": "text",
          "settings": {
            "text": "<p>We always love hearing from you.</p>"
          }
        }
      },
      "block_order": ["1651232402df3cc1c0-0", "1651232402df3cc1c0-1"],
      "settings": {
        "color_scheme": "background-1",
        "full_width": true,
        "padding_top": 40,
        "padding_bottom": 52
      }
    },
    "form": {
      "type": "contact-form",
      "settings": {
        "heading": "",
        "color_scheme": "background-1",
        "padding_top": 36,
        "padding_bottom": 100
      }
    }
  },
  "order": ["16468903570d47cd4d", "16512324026110f03c", "form"]
}
